caesar_cipher/__init__.py
caesar_cipher/cli.py
caesar_cipher/core.py
caesar_cipher_cli-0.1.2.dist-info/licenses/LICENSE
caesar_cipher_cli-0.1.2.dist-info/METADATA
caesar_cipher_cli-0.1.2.dist-info/WHEEL
caesar_cipher_cli-0.1.2.dist-info/entry_points.txt
caesar_cipher_cli-0.1.2.dist-info/top_level.txt
caesar_cipher_cli-0.1.2.dist-info/RECORD
