Metadata-Version: 2.4
Name: caesar-cipher-cli
Version: 0.1.2
Summary: A command-line tool for Caesar cipher encryption and decryption
Author: Santhosh Kumar Nethula
License: LICENSE
Project-URL: Homepage, https://github.com/Santhosh2949
Project-URL: Source, https://github.com/Santhosh2949/caesar-cipher-cli
Requires-Python: >=3.8
License-File: LICENSE
Dynamic: license-file
